checker/__init__.py
checker/cds_python_api.py
checker/ceda_cli.py
checker/copernicus_cli.py
checker/copernicus_python_api.py
copernicus_checker-1.0.1.dist-info/METADATA
copernicus_checker-1.0.1.dist-info/WHEEL
copernicus_checker-1.0.1.dist-info/entry_points.txt
copernicus_checker-1.0.1.dist-info/top_level.txt
copernicus_checker-1.0.1.dist-info/RECORD
