Metadata-Version: 2.1
Name: copernicus_checker
Version: 1.0.1
Summary: Copernicus Marine API with MongoDB duplication checking.
Home-page: https://github.com/yourusername/copernicus_checker
Author: Your Name
Author-email: your.email@example.com
Classifier: Programming Language :: Python :: 3
Classifier: License :: OSI Approved :: MIT License
Classifier: Operating System :: OS Independent
Requires-Python: >=3.7
Requires-Dist: pymongo
Requires-Dist: copernicusmarine
